django_informixdb/__init__.py
django_informixdb/base.py
django_informixdb/client.py
django_informixdb/compiler.py
django_informixdb/creation.py
django_informixdb/datatypes.py
django_informixdb/features.py
django_informixdb/fields.py
django_informixdb/introspection.py
django_informixdb/operations.py
django_informixdb/schema.py
django_informixdb/tableignore.py
django_informixdb/utils.py
test/__init__.py
test/conftest.py
test/test_base.py
test/test_integration.py
test/urls.py
test/datatypes/__init__.py
test/datatypes/models.py
test/datatypes/test_datatypes.py
django_informixdb-1.9.0.dist-info/LICENSE
django_informixdb-1.9.0.dist-info/METADATA
django_informixdb-1.9.0.dist-info/WHEEL
django_informixdb-1.9.0.dist-info/top_level.txt
django_informixdb-1.9.0.dist-info/RECORD
