Metadata-Version: 2.1
Name: django-informixdb
Version: 1.9.0
Summary: A database driver for Django to connect to an Informix db via ODBC
Home-page: https://github.com/reecetech/django_informixdb
Author: Reecetech
Author-email: opensource@reecetech.com.au
License: APLv2
Keywords: django informix
Platform: UNKNOWN
Classifier: Development Status :: 5 - Production/Stable
Classifier: Intended Audience :: Developers
Classifier: Topic :: Software Development
Classifier: Topic :: Scientific/Engineering
Classifier: License :: OSI Approved :: Apache Software License
Classifier: Programming Language :: Python :: 3
Classifier: Programming Language :: Python :: 3.5
Classifier: Programming Language :: Python :: 3.6
Requires-Dist: django (>=1.9.6)
Requires-Dist: pyodbc (>=4.0.21)
Provides-Extra: dev
Requires-Dist: check-manifest ; extra == 'dev'
Provides-Extra: test
Requires-Dist: coverage ; extra == 'test'
